{
  "fecha": "2026-07-21",
  "generado": "2026-07-21T10:52:01.836630-05:00",
  "solo_hoy": true,
  "fallback_multi_dia": false,
  "publicos": [
    {
      "partido": "Víkingur Reykjavík vs Hapoel Be'er Sheva",
      "local": "Víkingur Reykjavík",
      "visitante": "Hapoel Be'er Sheva",
      "liga": "comp_3498",
      "liga_nombre": "UEFA Champions League",
      "fecha": "2026-07-21",
      "hora": "14:00",
      "mercado": "Menos de 2.5 goles",
      "prob": 96.5,
      "cuota": 2.06,
      "cuota_display": 2.06,
      "ev": 0.48,
      "emoji": "🔒",
      "categoria": "Goles",
      "descripcion": "xG total 0.70",
      "fuente": "real",
      "tipo": "individual",
      "estado": "Pendiente",
      "ganancia": 0,
      "stake": 0
    },
    {
      "partido": "SK Sturm Graz vs Heart of Midlothian",
      "local": "SK Sturm Graz",
      "visitante": "Heart of Midlothian",
      "liga": "comp_3498",
      "liga_nombre": "UEFA Champions League",
      "fecha": "2026-07-21",
      "hora": "13:30",
      "mercado": "Victoria Heart of Midlothian",
      "prob": 76.6,
      "cuota": 4.16,
      "cuota_display": 4.16,
      "ev": 0.526,
      "emoji": "⚽",
      "categoria": "1X2",
      "descripcion": "xG 2.69 — modelo 76.6%",
      "fuente": "real",
      "tipo": "individual",
      "estado": "Pendiente",
      "ganancia": 0,
      "stake": 0
    },
    {
      "partido": "Libertad vs Delfín",
      "local": "Libertad",
      "visitante": "Delfín",
      "liga": "comp_1917",
      "liga_nombre": "LigaPro Serie A Ecuador",
      "fecha": "2026-07-21",
      "hora": "16:30",
      "mercado": "Victoria Libertad",
      "prob": 69.9,
      "cuota": 2.31,
      "cuota_display": 2.31,
      "ev": 0.266,
      "emoji": "⚽",
      "categoria": "1X2",
      "descripcion": "xG 1.96 — modelo 69.9%",
      "fuente": "real",
      "tipo": "individual",
      "estado": "Pendiente",
      "ganancia": 0,
      "stake": 0
    }
  ],
  "premium": [
    {
      "partido": "Víkingur Reykjavík vs Hapoel Be'er Sheva",
      "local": "Víkingur Reykjavík",
      "visitante": "Hapoel Be'er Sheva",
      "liga": "comp_3498",
      "liga_nombre": "UEFA Champions League",
      "fecha": "2026-07-21",
      "hora": "14:00",
      "mercado": "Combinada: Menos de 2.5 goles + X2 — Empate o Hapoel Be'er Sheva",
      "prob": 65.9,
      "cuota": 2.72,
      "cuota_display": 2.72,
      "ev": 0.792,
      "emoji": "🎯",
      "categoria": "Combinada",
      "descripcion": "Menos de 2.5 goles (96%) × X2 — Empate o Hapoel Be'er Sheva (68%)",
      "fuente": "real",
      "tipo": "premium",
      "estado": "Pendiente",
      "ganancia": 0,
      "stake": 0,
      "picks_combo": [
        {
          "mercado": "Menos de 2.5 goles",
          "cuota": 2.06
        },
        {
          "mercado": "X2 — Empate o Hapoel Be'er Sheva",
          "cuota": 1.32
        }
      ]
    }
  ],
  "todos_candidatos": [
    {
      "partido": "Universidad Católica del Ecuador vs Barcelona SC",
      "local": "Universidad Católica del Ecuador",
      "visitante": "Barcelona SC",
      "liga": "comp_1917",
      "liga_nombre": "LigaPro Serie A Ecuador",
      "fecha": "2026-07-21",
      "hora": "19:00",
      "mercado": "Victoria Universidad Católica del Ecuador",
      "prob": 58.0,
      "cuota": 1.9,
      "cuota_display": 1.9,
      "ev": 0.054,
      "emoji": "⚽",
      "categoria": "1X2",
      "descripcion": "xG 2.04 — modelo 58.0%",
      "fuente": "real",
      "tipo": "individual",
      "estado": "Pendiente",
      "ganancia": 0,
      "stake": 0
    },
    {
      "partido": "Universidad Católica del Ecuador vs Barcelona SC",
      "local": "Universidad Católica del Ecuador",
      "visitante": "Barcelona SC",
      "liga": "comp_1917",
      "liga_nombre": "LigaPro Serie A Ecuador",
      "fecha": "2026-07-21",
      "hora": "19:00",
      "mercado": "Más de 2.5 goles",
      "prob": 59.6,
      "cuota": 2.08,
      "cuota_display": 2.08,
      "ev": 0.115,
      "emoji": "🥅",
      "categoria": "Goles",
      "descripcion": "xG total 3.08",
      "fuente": "real",
      "tipo": "individual",
      "estado": "Pendiente",
      "ganancia": 0,
      "stake": 0
    },
    {
      "partido": "Universidad Católica del Ecuador vs Barcelona SC",
      "local": "Universidad Católica del Ecuador",
      "visitante": "Barcelona SC",
      "liga": "comp_1917",
      "liga_nombre": "LigaPro Serie A Ecuador",
      "fecha": "2026-07-21",
      "hora": "19:00",
      "mercado": "Ambos anotan - Sí",
      "prob": 56.4,
      "cuota": 1.77,
      "cuota_display": 1.77,
      "ev": -0.001,
      "emoji": "⚽",
      "categoria": "Goles",
      "descripcion": "Prob BTTS: 56.4%",
      "fuente": "real",
      "tipo": "individual",
      "estado": "Pendiente",
      "ganancia": 0,
      "stake": 0
    },
    {
      "partido": "FC Ararat-Armenia vs Shamrock Rovers",
      "local": "FC Ararat-Armenia",
      "visitante": "Shamrock Rovers",
      "liga": "comp_3498",
      "liga_nombre": "UEFA Champions League",
      "fecha": "2026-07-21",
      "hora": "11:00",
      "mercado": "Menos de 2.5 goles",
      "prob": 59.5,
      "cuota": 1.77,
      "cuota_display": 1.77,
      "ev": 0.03,
      "emoji": "🔒",
      "categoria": "Goles",
      "descripcion": "xG total 2.32",
      "fuente": "real",
      "tipo": "individual",
      "estado": "Pendiente",
      "ganancia": 0,
      "stake": 0
    },
    {
      "partido": "FC Ararat-Armenia vs Shamrock Rovers",
      "local": "FC Ararat-Armenia",
      "visitante": "Shamrock Rovers",
      "liga": "comp_3498",
      "liga_nombre": "UEFA Champions League",
      "fecha": "2026-07-21",
      "hora": "11:00",
      "mercado": "Ambos anotan - No",
      "prob": 53.6,
      "cuota": 1.87,
      "cuota_display": 1.87,
      "ev": 0.001,
      "emoji": "🔒",
      "categoria": "Goles",
      "descripcion": "Prob BTTS No: 53.6%",
      "fuente": "real",
      "tipo": "individual",
      "estado": "Pendiente",
      "ganancia": 0,
      "stake": 0
    },
    {
      "partido": "Mjällby AIF vs Lincoln Red Imps",
      "local": "Mjällby AIF",
      "visitante": "Lincoln Red Imps",
      "liga": "comp_3498",
      "liga_nombre": "UEFA Champions League",
      "fecha": "2026-07-21",
      "hora": "11:00",
      "mercado": "Menos de 2.5 goles",
      "prob": 64.8,
      "cuota": 2.5,
      "cuota_display": 2.5,
      "ev": 0.248,
      "emoji": "🔒",
      "categoria": "Goles",
      "descripcion": "xG total 2.11",
      "fuente": "real",
      "tipo": "individual",
      "estado": "Pendiente",
      "ganancia": 0,
      "stake": 0
    },
    {
      "partido": "Mjällby AIF vs Lincoln Red Imps",
      "local": "Mjällby AIF",
      "visitante": "Lincoln Red Imps",
      "liga": "comp_3498",
      "liga_nombre": "UEFA Champions League",
      "fecha": "2026-07-21",
      "hora": "11:00",
      "mercado": "Ambos anotan - No",
      "prob": 63.8,
      "cuota": 1.57,
      "cuota_display": 1.57,
      "ev": 0.001,
      "emoji": "🔒",
      "categoria": "Goles",
      "descripcion": "Prob BTTS No: 63.8%",
      "fuente": "real",
      "tipo": "individual",
      "estado": "Pendiente",
      "ganancia": 0,
      "stake": 0
    },
    {
      "partido": "Sabah FK vs KuPS",
      "local": "Sabah FK",
      "visitante": "KuPS",
      "liga": "comp_3498",
      "liga_nombre": "UEFA Champions League",
      "fecha": "2026-07-21",
      "hora": "11:00",
      "mercado": "Victoria Sabah FK",
      "prob": 50.2,
      "cuota": 1.64,
      "cuota_display": 1.64,
      "ev": -0.108,
      "emoji": "⚽",
      "categoria": "1X2",
      "descripcion": "xG 1.11 — modelo 50.2%",
      "fuente": "real",
      "tipo": "individual",
      "estado": "Pendiente",
      "ganancia": 0,
      "stake": 0
    },
    {
      "partido": "Sabah FK vs KuPS",
      "local": "Sabah FK",
      "visitante": "KuPS",
      "liga": "comp_3498",
      "liga_nombre": "UEFA Champions League",
      "fecha": "2026-07-21",
      "hora": "11:00",
      "mercado": "Menos de 2.5 goles",
      "prob": 80.2,
      "cuota": 2.13,
      "cuota_display": 2.13,
      "ev": 0.333,
      "emoji": "🔒",
      "categoria": "Goles",
      "descripcion": "xG total 1.53",
      "fuente": "real",
      "tipo": "individual",
      "estado": "Pendiente",
      "ganancia": 0,
      "stake": 0
    },
    {
      "partido": "AGF vs Lech Poznań",
      "local": "AGF",
      "visitante": "Lech Poznań",
      "liga": "comp_3498",
      "liga_nombre": "UEFA Champions League",
      "fecha": "2026-07-21",
      "hora": "12:00",
      "mercado": "Menos de 2.5 goles",
      "prob": 50.1,
      "cuota": 1.61,
      "cuota_display": 1.61,
      "ev": -0.12,
      "emoji": "🔒",
      "categoria": "Goles",
      "descripcion": "xG total 2.68",
      "fuente": "real",
      "tipo": "individual",
      "estado": "Pendiente",
      "ganancia": 0,
      "stake": 0
    },
    {
      "partido": "AGF vs Lech Poznań",
      "local": "AGF",
      "visitante": "Lech Poznań",
      "liga": "comp_3498",
      "liga_nombre": "UEFA Champions League",
      "fecha": "2026-07-21",
      "hora": "12:00",
      "mercado": "Ambos anotan - Sí",
      "prob": 52.8,
      "cuota": 1.89,
      "cuota_display": 1.89,
      "ev": -0.001,
      "emoji": "⚽",
      "categoria": "Goles",
      "descripcion": "Prob BTTS: 52.8%",
      "fuente": "real",
      "tipo": "individual",
      "estado": "Pendiente",
      "ganancia": 0,
      "stake": 0
    },
    {
      "partido": "Fenerbahçe vs Górnik Zabrze",
      "local": "Fenerbahçe",
      "visitante": "Górnik Zabrze",
      "liga": "comp_3498",
      "liga_nombre": "UEFA Champions League",
      "fecha": "2026-07-21",
      "hora": "13:00",
      "mercado": "Menos de 2.5 goles",
      "prob": 84.9,
      "cuota": 2.88,
      "cuota_display": 2.88,
      "ev": 0.502,
      "emoji": "🔒",
      "categoria": "Goles",
      "descripcion": "xG total 1.35",
      "fuente": "real",
      "tipo": "individual",
      "estado": "Pendiente",
      "ganancia": 0,
      "stake": 0
    },
    {
      "partido": "Fenerbahçe vs Górnik Zabrze",
      "local": "Fenerbahçe",
      "visitante": "Górnik Zabrze",
      "liga": "comp_3498",
      "liga_nombre": "UEFA Champions League",
      "fecha": "2026-07-21",
      "hora": "13:00",
      "mercado": "Ambos anotan - No",
      "prob": 75.9,
      "cuota": 1.32,
      "cuota_display": 1.32,
      "ev": 0.001,
      "emoji": "🔒",
      "categoria": "Goles",
      "descripcion": "Prob BTTS No: 75.9%",
      "fuente": "real",
      "tipo": "individual",
      "estado": "Pendiente",
      "ganancia": 0,
      "stake": 0
    },
    {
      "partido": "Fenerbahçe vs Górnik Zabrze",
      "local": "Fenerbahçe",
      "visitante": "Górnik Zabrze",
      "liga": "comp_3498",
      "liga_nombre": "UEFA Champions League",
      "fecha": "2026-07-21",
      "hora": "13:00",
      "mercado": "X2 — Empate o Górnik Zabrze",
      "prob": 64.9,
      "cuota": 1.39,
      "cuota_display": 1.39,
      "ev": -0.07,
      "emoji": "🛡️",
      "categoria": "Doble Op.",
      "descripcion": "Sin derrota Górnik Zabrze: 64.9%",
      "fuente": "real",
      "tipo": "individual",
      "estado": "Pendiente",
      "ganancia": 0,
      "stake": 0
    },
    {
      "partido": "FC Thun vs GNK Dinamo Zagreb",
      "local": "FC Thun",
      "visitante": "GNK Dinamo Zagreb",
      "liga": "comp_3498",
      "liga_nombre": "UEFA Champions League",
      "fecha": "2026-07-21",
      "hora": "13:00",
      "mercado": "Menos de 2.5 goles",
      "prob": 90.0,
      "cuota": 2.24,
      "cuota_display": 2.24,
      "ev": 0.454,
      "emoji": "🔒",
      "categoria": "Goles",
      "descripcion": "xG total 1.11",
      "fuente": "real",
      "tipo": "individual",
      "estado": "Pendiente",
      "ganancia": 0,
      "stake": 0
    },
    {
      "partido": "Universidad Central vs Santos",
      "local": "Universidad Central",
      "visitante": "Santos",
      "liga": "comp_1615",
      "liga_nombre": "CONMEBOL Sudamericana",
      "fecha": "2026-07-21",
      "hora": "19:30",
      "mercado": "Más de 2.5 goles",
      "prob": 62.3,
      "cuota": 2.07,
      "cuota_display": 2.07,
      "ev": 0.14,
      "emoji": "🥅",
      "categoria": "Goles",
      "descripcion": "xG total 3.23",
      "fuente": "real",
      "tipo": "individual",
      "estado": "Pendiente",
      "ganancia": 0,
      "stake": 0
    },
    {
      "partido": "Universidad Central vs Santos",
      "local": "Universidad Central",
      "visitante": "Santos",
      "liga": "comp_1615",
      "liga_nombre": "CONMEBOL Sudamericana",
      "fecha": "2026-07-21",
      "hora": "19:30",
      "mercado": "Ambos anotan - Sí",
      "prob": 64.1,
      "cuota": 1.56,
      "cuota_display": 1.56,
      "ev": -0.0,
      "emoji": "⚽",
      "categoria": "Goles",
      "descripcion": "Prob BTTS: 64.1%",
      "fuente": "real",
      "tipo": "individual",
      "estado": "Pendiente",
      "ganancia": 0,
      "stake": 0
    },
    {
      "partido": "Universidad Central vs Santos",
      "local": "Universidad Central",
      "visitante": "Santos",
      "liga": "comp_1615",
      "liga_nombre": "CONMEBOL Sudamericana",
      "fecha": "2026-07-21",
      "hora": "19:30",
      "mercado": "1X — Universidad Central o Empate",
      "prob": 63.6,
      "cuota": 1.42,
      "cuota_display": 1.42,
      "ev": -0.068,
      "emoji": "🛡️",
      "categoria": "Doble Op.",
      "descripcion": "Sin derrota Universidad Central: 63.6%",
      "fuente": "real",
      "tipo": "individual",
      "estado": "Pendiente",
      "ganancia": 0,
      "stake": 0
    },
    {
      "partido": "Universidad Central vs Santos",
      "local": "Universidad Central",
      "visitante": "Santos",
      "liga": "comp_1615",
      "liga_nombre": "CONMEBOL Sudamericana",
      "fecha": "2026-07-21",
      "hora": "19:30",
      "mercado": "X2 — Empate o Santos",
      "prob": 61.9,
      "cuota": 1.45,
      "cuota_display": 1.45,
      "ev": -0.071,
      "emoji": "🛡️",
      "categoria": "Doble Op.",
      "descripcion": "Sin derrota Santos: 61.9%",
      "fuente": "real",
      "tipo": "individual",
      "estado": "Pendiente",
      "ganancia": 0,
      "stake": 0
    },
    {
      "partido": "Atlético Mineiro vs Bahia",
      "local": "Atlético Mineiro",
      "visitante": "Bahia",
      "liga": "comp_4795",
      "liga_nombre": "Brasileirão Série A",
      "fecha": "2026-07-21",
      "hora": "17:30",
      "mercado": "Más de 2.5 goles",
      "prob": 51.2,
      "cuota": 1.94,
      "cuota_display": 1.94,
      "ev": -0.003,
      "emoji": "🥅",
      "categoria": "Goles",
      "descripcion": "xG total 2.73",
      "fuente": "real",
      "tipo": "individual",
      "estado": "Pendiente",
      "ganancia": 0,
      "stake": 0
    },
    {
      "partido": "Atlético Mineiro vs Bahia",
      "local": "Atlético Mineiro",
      "visitante": "Bahia",
      "liga": "comp_4795",
      "liga_nombre": "Brasileirão Série A",
      "fecha": "2026-07-21",
      "hora": "17:30",
      "mercado": "Ambos anotan - Sí",
      "prob": 52.7,
      "cuota": 1.9,
      "cuota_display": 1.9,
      "ev": 0.001,
      "emoji": "⚽",
      "categoria": "Goles",
      "descripcion": "Prob BTTS: 52.7%",
      "fuente": "real",
      "tipo": "individual",
      "estado": "Pendiente",
      "ganancia": 0,
      "stake": 0
    },
    {
      "partido": "Klaksvíkar Ítróttarfelag vs FK Kauno Žalgiris",
      "local": "Klaksvíkar Ítróttarfelag",
      "visitante": "FK Kauno Žalgiris",
      "liga": "comp_3498",
      "liga_nombre": "UEFA Champions League",
      "fecha": "2026-07-21",
      "hora": "13:45",
      "mercado": "Menos de 2.5 goles",
      "prob": 80.1,
      "cuota": 1.53,
      "cuota_display": 1.53,
      "ev": 0.147,
      "emoji": "🔒",
      "categoria": "Goles",
      "descripcion": "xG total 1.52",
      "fuente": "real",
      "tipo": "individual",
      "estado": "Pendiente",
      "ganancia": 0,
      "stake": 0
    },
    {
      "partido": "Klaksvíkar Ítróttarfelag vs FK Kauno Žalgiris",
      "local": "Klaksvíkar Ítróttarfelag",
      "visitante": "FK Kauno Žalgiris",
      "liga": "comp_3498",
      "liga_nombre": "UEFA Champions League",
      "fecha": "2026-07-21",
      "hora": "13:45",
      "mercado": "Ambos anotan - No",
      "prob": 74.7,
      "cuota": 1.34,
      "cuota_display": 1.34,
      "ev": 0.001,
      "emoji": "🔒",
      "categoria": "Goles",
      "descripcion": "Prob BTTS No: 74.7%",
      "fuente": "real",
      "tipo": "individual",
      "estado": "Pendiente",
      "ganancia": 0,
      "stake": 0
    },
    {
      "partido": "Víkingur Reykjavík vs Hapoel Be'er Sheva",
      "local": "Víkingur Reykjavík",
      "visitante": "Hapoel Be'er Sheva",
      "liga": "comp_3498",
      "liga_nombre": "UEFA Champions League",
      "fecha": "2026-07-21",
      "hora": "14:00",
      "mercado": "Empate",
      "prob": 53.9,
      "cuota": 3.47,
      "cuota_display": 3.47,
      "ev": 0.251,
      "emoji": "🤝",
      "categoria": "1X2",
      "descripcion": "xG total 0.70",
      "fuente": "real",
      "tipo": "individual",
      "estado": "Pendiente",
      "ganancia": 0,
      "stake": 0
    },
    {
      "partido": "Víkingur Reykjavík vs Hapoel Be'er Sheva",
      "local": "Víkingur Reykjavík",
      "visitante": "Hapoel Be'er Sheva",
      "liga": "comp_3498",
      "liga_nombre": "UEFA Champions League",
      "fecha": "2026-07-21",
      "hora": "14:00",
      "mercado": "Menos de 2.5 goles",
      "prob": 96.5,
      "cuota": 2.06,
      "cuota_display": 2.06,
      "ev": 0.48,
      "emoji": "🔒",
      "categoria": "Goles",
      "descripcion": "xG total 0.70",
      "fuente": "real",
      "tipo": "individual",
      "estado": "Pendiente",
      "ganancia": 0,
      "stake": 0
    },
    {
      "partido": "Víkingur Reykjavík vs Hapoel Be'er Sheva",
      "local": "Víkingur Reykjavík",
      "visitante": "Hapoel Be'er Sheva",
      "liga": "comp_3498",
      "liga_nombre": "UEFA Champions League",
      "fecha": "2026-07-21",
      "hora": "14:00",
      "mercado": "X2 — Empate o Hapoel Be'er Sheva",
      "prob": 68.3,
      "cuota": 1.32,
      "cuota_display": 1.32,
      "ev": -0.075,
      "emoji": "🛡️",
      "categoria": "Doble Op.",
      "descripcion": "Sin derrota Hapoel Be'er Sheva: 68.3%",
      "fuente": "real",
      "tipo": "individual",
      "estado": "Pendiente",
      "ganancia": 0,
      "stake": 0
    },
    {
      "partido": "Larne FC vs FK Crvena zvezda",
      "local": "Larne FC",
      "visitante": "FK Crvena zvezda",
      "liga": "comp_3498",
      "liga_nombre": "UEFA Champions League",
      "fecha": "2026-07-21",
      "hora": "14:00",
      "mercado": "Menos de 2.5 goles",
      "prob": 81.2,
      "cuota": 2.25,
      "cuota_display": 2.25,
      "ev": 0.368,
      "emoji": "🔒",
      "categoria": "Goles",
      "descripcion": "xG total 1.48",
      "fuente": "real",
      "tipo": "individual",
      "estado": "Pendiente",
      "ganancia": 0,
      "stake": 0
    },
    {
      "partido": "Larne FC vs FK Crvena zvezda",
      "local": "Larne FC",
      "visitante": "FK Crvena zvezda",
      "liga": "comp_3498",
      "liga_nombre": "UEFA Champions League",
      "fecha": "2026-07-21",
      "hora": "14:00",
      "mercado": "Ambos anotan - No",
      "prob": 76.4,
      "cuota": 1.31,
      "cuota_display": 1.31,
      "ev": 0.001,
      "emoji": "🔒",
      "categoria": "Goles",
      "descripcion": "Prob BTTS No: 76.4%",
      "fuente": "real",
      "tipo": "individual",
      "estado": "Pendiente",
      "ganancia": 0,
      "stake": 0
    },
    {
      "partido": "Libertad vs Delfín",
      "local": "Libertad",
      "visitante": "Delfín",
      "liga": "comp_1917",
      "liga_nombre": "LigaPro Serie A Ecuador",
      "fecha": "2026-07-21",
      "hora": "16:30",
      "mercado": "Victoria Libertad",
      "prob": 69.9,
      "cuota": 2.31,
      "cuota_display": 2.31,
      "ev": 0.266,
      "emoji": "⚽",
      "categoria": "1X2",
      "descripcion": "xG 1.96 — modelo 69.9%",
      "fuente": "real",
      "tipo": "individual",
      "estado": "Pendiente",
      "ganancia": 0,
      "stake": 0
    },
    {
      "partido": "Libertad vs Delfín",
      "local": "Libertad",
      "visitante": "Delfín",
      "liga": "comp_1917",
      "liga_nombre": "LigaPro Serie A Ecuador",
      "fecha": "2026-07-21",
      "hora": "16:30",
      "mercado": "Menos de 2.5 goles",
      "prob": 56.0,
      "cuota": 1.53,
      "cuota_display": 1.53,
      "ev": -0.094,
      "emoji": "🔒",
      "categoria": "Goles",
      "descripcion": "xG total 2.43",
      "fuente": "real",
      "tipo": "individual",
      "estado": "Pendiente",
      "ganancia": 0,
      "stake": 0
    },
    {
      "partido": "Libertad vs Delfín",
      "local": "Libertad",
      "visitante": "Delfín",
      "liga": "comp_1917",
      "liga_nombre": "LigaPro Serie A Ecuador",
      "fecha": "2026-07-21",
      "hora": "16:30",
      "mercado": "Ambos anotan - No",
      "prob": 68.0,
      "cuota": 1.47,
      "cuota_display": 1.47,
      "ev": -0.0,
      "emoji": "🔒",
      "categoria": "Goles",
      "descripcion": "Prob BTTS No: 68.0%",
      "fuente": "real",
      "tipo": "individual",
      "estado": "Pendiente",
      "ganancia": 0,
      "stake": 0
    },
    {
      "partido": "Cruz Azul vs Club Puebla",
      "local": "Cruz Azul",
      "visitante": "Club Puebla",
      "liga": "comp_298265",
      "liga_nombre": "Liga MX Apertura",
      "fecha": "2026-07-21",
      "hora": "20:00",
      "mercado": "Victoria Cruz Azul",
      "prob": 70.7,
      "cuota": 1.31,
      "cuota_display": 1.31,
      "ev": -0.056,
      "emoji": "⚽",
      "categoria": "1X2",
      "descripcion": "xG 2.42 — modelo 70.7%",
      "fuente": "real",
      "tipo": "individual",
      "estado": "Pendiente",
      "ganancia": 0,
      "stake": 0
    },
    {
      "partido": "Cruz Azul vs Club Puebla",
      "local": "Cruz Azul",
      "visitante": "Club Puebla",
      "liga": "comp_298265",
      "liga_nombre": "Liga MX Apertura",
      "fecha": "2026-07-21",
      "hora": "20:00",
      "mercado": "Más de 2.5 goles",
      "prob": 61.2,
      "cuota": 1.65,
      "cuota_display": 1.65,
      "ev": 0.006,
      "emoji": "🥅",
      "categoria": "Goles",
      "descripcion": "xG total 3.15",
      "fuente": "real",
      "tipo": "individual",
      "estado": "Pendiente",
      "ganancia": 0,
      "stake": 0
    },
    {
      "partido": "Cruz Azul vs Club Puebla",
      "local": "Cruz Azul",
      "visitante": "Club Puebla",
      "liga": "comp_298265",
      "liga_nombre": "Liga MX Apertura",
      "fecha": "2026-07-21",
      "hora": "20:00",
      "mercado": "Ambos anotan - No",
      "prob": 52.7,
      "cuota": 1.9,
      "cuota_display": 1.9,
      "ev": 0.001,
      "emoji": "🔒",
      "categoria": "Goles",
      "descripcion": "Prob BTTS No: 52.7%",
      "fuente": "real",
      "tipo": "individual",
      "estado": "Pendiente",
      "ganancia": 0,
      "stake": 0
    },
    {
      "partido": "CD Toluca vs Pumas UNAM",
      "local": "CD Toluca",
      "visitante": "Pumas UNAM",
      "liga": "comp_298265",
      "liga_nombre": "Liga MX Apertura",
      "fecha": "2026-07-21",
      "hora": "22:05",
      "mercado": "Victoria CD Toluca",
      "prob": 66.2,
      "cuota": 1.59,
      "cuota_display": 1.59,
      "ev": 0.033,
      "emoji": "⚽",
      "categoria": "1X2",
      "descripcion": "xG 2.18 — modelo 66.2%",
      "fuente": "real",
      "tipo": "individual",
      "estado": "Pendiente",
      "ganancia": 0,
      "stake": 0
    },
    {
      "partido": "CD Toluca vs Pumas UNAM",
      "local": "CD Toluca",
      "visitante": "Pumas UNAM",
      "liga": "comp_298265",
      "liga_nombre": "Liga MX Apertura",
      "fecha": "2026-07-21",
      "hora": "22:05",
      "mercado": "Más de 2.5 goles",
      "prob": 57.5,
      "cuota": 1.65,
      "cuota_display": 1.65,
      "ev": -0.031,
      "emoji": "🥅",
      "categoria": "Goles",
      "descripcion": "xG total 2.98",
      "fuente": "real",
      "tipo": "individual",
      "estado": "Pendiente",
      "ganancia": 0,
      "stake": 0
    },
    {
      "partido": "CD Toluca vs Pumas UNAM",
      "local": "CD Toluca",
      "visitante": "Pumas UNAM",
      "liga": "comp_298265",
      "liga_nombre": "Liga MX Apertura",
      "fecha": "2026-07-21",
      "hora": "22:05",
      "mercado": "Ambos anotan - No",
      "prob": 51.6,
      "cuota": 1.94,
      "cuota_display": 1.94,
      "ev": 0.001,
      "emoji": "🔒",
      "categoria": "Goles",
      "descripcion": "Prob BTTS No: 51.6%",
      "fuente": "real",
      "tipo": "individual",
      "estado": "Pendiente",
      "ganancia": 0,
      "stake": 0
    },
    {
      "partido": "SK Sturm Graz vs Heart of Midlothian",
      "local": "SK Sturm Graz",
      "visitante": "Heart of Midlothian",
      "liga": "comp_3498",
      "liga_nombre": "UEFA Champions League",
      "fecha": "2026-07-21",
      "hora": "13:30",
      "mercado": "Victoria Heart of Midlothian",
      "prob": 76.6,
      "cuota": 4.16,
      "cuota_display": 4.16,
      "ev": 0.526,
      "emoji": "⚽",
      "categoria": "1X2",
      "descripcion": "xG 2.69 — modelo 76.6%",
      "fuente": "real",
      "tipo": "individual",
      "estado": "Pendiente",
      "ganancia": 0,
      "stake": 0
    },
    {
      "partido": "SK Sturm Graz vs Heart of Midlothian",
      "local": "SK Sturm Graz",
      "visitante": "Heart of Midlothian",
      "liga": "comp_3498",
      "liga_nombre": "UEFA Champions League",
      "fecha": "2026-07-21",
      "hora": "13:30",
      "mercado": "Más de 2.5 goles",
      "prob": 62.7,
      "cuota": 1.75,
      "cuota_display": 1.75,
      "ev": 0.056,
      "emoji": "🥅",
      "categoria": "Goles",
      "descripcion": "xG total 3.25",
      "fuente": "real",
      "tipo": "individual",
      "estado": "Pendiente",
      "ganancia": 0,
      "stake": 0
    },
    {
      "partido": "SK Sturm Graz vs Heart of Midlothian",
      "local": "SK Sturm Graz",
      "visitante": "Heart of Midlothian",
      "liga": "comp_3498",
      "liga_nombre": "UEFA Champions League",
      "fecha": "2026-07-21",
      "hora": "13:30",
      "mercado": "Ambos anotan - No",
      "prob": 59.7,
      "cuota": 1.68,
      "cuota_display": 1.68,
      "ev": 0.002,
      "emoji": "🔒",
      "categoria": "Goles",
      "descripcion": "Prob BTTS No: 59.7%",
      "fuente": "real",
      "tipo": "individual",
      "estado": "Pendiente",
      "ganancia": 0,
      "stake": 0
    },
    {
      "partido": "Sabah FK vs FK Vardar Skopje",
      "local": "Sabah FK",
      "visitante": "FK Vardar Skopje",
      "liga": "comp_3498",
      "liga_nombre": "UEFA Champions League",
      "fecha": "2026-07-21",
      "hora": "08:00",
      "mercado": "Ambos anotan - No",
      "prob": 63.2,
      "cuota": 1.58,
      "cuota_display": 1.58,
      "ev": -0.001,
      "emoji": "🔒",
      "categoria": "Goles",
      "descripcion": "Prob BTTS No: 63.2%",
      "fuente": "real",
      "tipo": "individual",
      "estado": "Pendiente",
      "ganancia": 0,
      "stake": 0
    },
    {
      "partido": "FC Iberia 1999 vs ŠK Slovan Bratislava",
      "local": "FC Iberia 1999",
      "visitante": "ŠK Slovan Bratislava",
      "liga": "comp_3498",
      "liga_nombre": "UEFA Champions League",
      "fecha": "2026-07-21",
      "hora": "11:00",
      "mercado": "Menos de 2.5 goles",
      "prob": 64.4,
      "cuota": 2.15,
      "cuota_display": 2.15,
      "ev": 0.179,
      "emoji": "🔒",
      "categoria": "Goles",
      "descripcion": "xG total 2.11",
      "fuente": "real",
      "tipo": "individual",
      "estado": "Pendiente",
      "ganancia": 0,
      "stake": 0
    },
    {
      "partido": "FC Iberia 1999 vs ŠK Slovan Bratislava",
      "local": "FC Iberia 1999",
      "visitante": "ŠK Slovan Bratislava",
      "liga": "comp_3498",
      "liga_nombre": "UEFA Champions League",
      "fecha": "2026-07-21",
      "hora": "11:00",
      "mercado": "Ambos anotan - No",
      "prob": 60.4,
      "cuota": 1.66,
      "cuota_display": 1.66,
      "ev": 0.002,
      "emoji": "🔒",
      "categoria": "Goles",
      "descripcion": "Prob BTTS No: 60.4%",
      "fuente": "real",
      "tipo": "individual",
      "estado": "Pendiente",
      "ganancia": 0,
      "stake": 0
    },
    {
      "partido": "Nacional vs Tigre",
      "local": "Nacional",
      "visitante": "Tigre",
      "liga": "comp_1615",
      "liga_nombre": "CONMEBOL Sudamericana",
      "fecha": "2026-07-21",
      "hora": "17:00",
      "mercado": "Menos de 2.5 goles",
      "prob": 61.6,
      "cuota": 1.5,
      "cuota_display": 1.5,
      "ev": -0.051,
      "emoji": "🔒",
      "categoria": "Goles",
      "descripcion": "xG total 2.20",
      "fuente": "real",
      "tipo": "individual",
      "estado": "Pendiente",
      "ganancia": 0,
      "stake": 0
    },
    {
      "partido": "Nacional vs Tigre",
      "local": "Nacional",
      "visitante": "Tigre",
      "liga": "comp_1615",
      "liga_nombre": "CONMEBOL Sudamericana",
      "fecha": "2026-07-21",
      "hora": "17:00",
      "mercado": "Ambos anotan - No",
      "prob": 56.9,
      "cuota": 1.76,
      "cuota_display": 1.76,
      "ev": 0.001,
      "emoji": "🔒",
      "categoria": "Goles",
      "descripcion": "Prob BTTS No: 56.9%",
      "fuente": "real",
      "tipo": "individual",
      "estado": "Pendiente",
      "ganancia": 0,
      "stake": 0
    },
    {
      "partido": "Atert Bissen vs ETO FC Győr",
      "local": "Atert Bissen",
      "visitante": "ETO FC Győr",
      "liga": "comp_408698",
      "liga_nombre": "UEFA Conference League",
      "fecha": "2026-07-21",
      "hora": "13:15",
      "mercado": "Victoria ETO FC Győr",
      "prob": 57.2,
      "cuota": 1.5,
      "cuota_display": 1.5,
      "ev": -0.095,
      "emoji": "⚽",
      "categoria": "1X2",
      "descripcion": "xG 2.20 — modelo 57.2%",
      "fuente": "real",
      "tipo": "individual",
      "estado": "Pendiente",
      "ganancia": 0,
      "stake": 0
    },
    {
      "partido": "Atert Bissen vs ETO FC Győr",
      "local": "Atert Bissen",
      "visitante": "ETO FC Győr",
      "liga": "comp_408698",
      "liga_nombre": "UEFA Conference League",
      "fecha": "2026-07-21",
      "hora": "13:15",
      "mercado": "Más de 2.5 goles",
      "prob": 65.9,
      "cuota": 1.69,
      "cuota_display": 1.69,
      "ev": 0.067,
      "emoji": "🥅",
      "categoria": "Goles",
      "descripcion": "xG total 3.40",
      "fuente": "real",
      "tipo": "individual",
      "estado": "Pendiente",
      "ganancia": 0,
      "stake": 0
    },
    {
      "partido": "Atert Bissen vs ETO FC Győr",
      "local": "Atert Bissen",
      "visitante": "ETO FC Győr",
      "liga": "comp_408698",
      "liga_nombre": "UEFA Conference League",
      "fecha": "2026-07-21",
      "hora": "13:15",
      "mercado": "Ambos anotan - Sí",
      "prob": 62.4,
      "cuota": 1.6,
      "cuota_display": 1.6,
      "ev": -0.001,
      "emoji": "⚽",
      "categoria": "Goles",
      "descripcion": "Prob BTTS: 62.4%",
      "fuente": "real",
      "tipo": "individual",
      "estado": "Pendiente",
      "ganancia": 0,
      "stake": 0
    },
    {
      "partido": "Floriana FC vs FC Drita",
      "local": "Floriana FC",
      "visitante": "FC Drita",
      "liga": "comp_408698",
      "liga_nombre": "UEFA Conference League",
      "fecha": "2026-07-21",
      "hora": "12:30",
      "mercado": "Más de 2.5 goles",
      "prob": 64.5,
      "cuota": 1.7,
      "cuota_display": 1.7,
      "ev": 0.057,
      "emoji": "🥅",
      "categoria": "Goles",
      "descripcion": "xG total 3.33",
      "fuente": "real",
      "tipo": "individual",
      "estado": "Pendiente",
      "ganancia": 0,
      "stake": 0
    },
    {
      "partido": "Floriana FC vs FC Drita",
      "local": "Floriana FC",
      "visitante": "FC Drita",
      "liga": "comp_408698",
      "liga_nombre": "UEFA Conference League",
      "fecha": "2026-07-21",
      "hora": "12:30",
      "mercado": "Ambos anotan - Sí",
      "prob": 65.6,
      "cuota": 1.52,
      "cuota_display": 1.52,
      "ev": -0.002,
      "emoji": "⚽",
      "categoria": "Goles",
      "descripcion": "Prob BTTS: 65.6%",
      "fuente": "real",
      "tipo": "individual",
      "estado": "Pendiente",
      "ganancia": 0,
      "stake": 0
    },
    {
      "partido": "Floriana FC vs FC Drita",
      "local": "Floriana FC",
      "visitante": "FC Drita",
      "liga": "comp_408698",
      "liga_nombre": "UEFA Conference League",
      "fecha": "2026-07-21",
      "hora": "12:30",
      "mercado": "1X — Floriana FC o Empate",
      "prob": 65.2,
      "cuota": 1.38,
      "cuota_display": 1.38,
      "ev": -0.073,
      "emoji": "🛡️",
      "categoria": "Doble Op.",
      "descripcion": "Sin derrota Floriana FC: 65.2%",
      "fuente": "real",
      "tipo": "individual",
      "estado": "Pendiente",
      "ganancia": 0,
      "stake": 0
    },
    {
      "partido": "IFK Göteborg vs FCI Levadia Tallinn",
      "local": "IFK Göteborg",
      "visitante": "FCI Levadia Tallinn",
      "liga": "comp_408698",
      "liga_nombre": "UEFA Conference League",
      "fecha": "2026-07-21",
      "hora": "12:00",
      "mercado": "Victoria FCI Levadia Tallinn",
      "prob": 55.7,
      "cuota": 5.25,
      "cuota_display": 5.25,
      "ev": 0.367,
      "emoji": "⚽",
      "categoria": "1X2",
      "descripcion": "xG 1.58 — modelo 55.7%",
      "fuente": "real",
      "tipo": "individual",
      "estado": "Pendiente",
      "ganancia": 0,
      "stake": 0
    },
    {
      "partido": "IFK Göteborg vs FCI Levadia Tallinn",
      "local": "IFK Göteborg",
      "visitante": "FCI Levadia Tallinn",
      "liga": "comp_408698",
      "liga_nombre": "UEFA Conference League",
      "fecha": "2026-07-21",
      "hora": "12:00",
      "mercado": "Menos de 2.5 goles",
      "prob": 58.9,
      "cuota": 2.15,
      "cuota_display": 2.15,
      "ev": 0.124,
      "emoji": "🔒",
      "categoria": "Goles",
      "descripcion": "xG total 2.31",
      "fuente": "real",
      "tipo": "individual",
      "estado": "Pendiente",
      "ganancia": 0,
      "stake": 0
    },
    {
      "partido": "IFK Göteborg vs FCI Levadia Tallinn",
      "local": "IFK Göteborg",
      "visitante": "FCI Levadia Tallinn",
      "liga": "comp_408698",
      "liga_nombre": "UEFA Conference League",
      "fecha": "2026-07-21",
      "hora": "12:00",
      "mercado": "Ambos anotan - No",
      "prob": 58.4,
      "cuota": 1.71,
      "cuota_display": 1.71,
      "ev": -0.001,
      "emoji": "🔒",
      "categoria": "Goles",
      "descripcion": "Prob BTTS No: 58.4%",
      "fuente": "real",
      "tipo": "individual",
      "estado": "Pendiente",
      "ganancia": 0,
      "stake": 0
    }
  ]
}